qphase/__init__.py
qphase/__main__.py
qphase/main.py
qphase/backend/__init__.py
qphase/backend/base.py
qphase/backend/cupy_backend.py
qphase/backend/numba_backend.py
qphase/backend/numpy_backend.py
qphase/backend/torch_backend.py
qphase/backend/xputil.py
qphase/commands/__init__.py
qphase/commands/config.py
qphase/commands/init.py
qphase/commands/plugin.py
qphase/commands/run.py
qphase/core/__init__.py
qphase/core/config.py
qphase/core/config_loader.py
qphase/core/errors.py
qphase/core/job_expansion.py
qphase/core/protocols.py
qphase/core/registry.py
qphase/core/result_loader.py
qphase/core/scheduler.py
qphase/core/snapshot.py
qphase/core/system.yaml
qphase/core/system_config.py
qphase/core/utils.py
qphase-1.0.0.dist-info/licenses/LICENSE
qphase-1.0.0.dist-info/METADATA
qphase-1.0.0.dist-info/WHEEL
qphase-1.0.0.dist-info/entry_points.txt
qphase-1.0.0.dist-info/top_level.txt
qphase-1.0.0.dist-info/RECORD
