Metadata-Version: 2.4
Name: qphase
Version: 1.0.0
Summary: Modular Quantum Phase-Space Simulation Framework (Core & CLI)
Author-email: Yu Xue-Hao <yuxuehao23@mails.ucas.ac.cn>
License: MIT License
Project-URL: Homepage, https://github.com/PolarisMegrez/qphase
Project-URL: Repository, https://github.com/PolarisMegrez/qphase
Project-URL: Issues, https://github.com/PolarisMegrez/qphase/issues
Keywords: quantum optics,SDE,simulation,CLI,Typer
Classifier: Programming Language :: Python :: 3
Classifier: Programming Language :: Python :: 3.10
Classifier: Programming Language :: Python :: 3.11
Classifier: Programming Language :: Python :: 3.12
Classifier: License :: OSI Approved :: MIT License
Classifier: Operating System :: OS Independent
Classifier: Intended Audience :: Science/Research
Classifier: Topic :: Scientific/Engineering :: Physics
Classifier: Topic :: Software Development :: Libraries
Requires-Python: >=3.10
License-File: LICENSE
Requires-Dist: typer>=0.9
Requires-Dist: rich>=13.0
Requires-Dist: ruamel.yaml>=0.17
Requires-Dist: PyYAML>=6.0
Requires-Dist: pydantic>=2.0
Provides-Extra: numba
Requires-Dist: numba>=0.57; extra == "numba"
Provides-Extra: cupy
Requires-Dist: cupy-cuda12x>=12.0; extra == "cupy"
Provides-Extra: torch
Requires-Dist: torch>=2.0; extra == "torch"
Provides-Extra: standard
Requires-Dist: numba>=0.57; extra == "standard"
Requires-Dist: torch>=2.0; extra == "standard"
Dynamic: license-file
